aioruz/__init__.py
aioruz/api.py
aioruz-0.8.0.dist-info/LICENSE
aioruz-0.8.0.dist-info/METADATA
aioruz-0.8.0.dist-info/WHEEL
aioruz-0.8.0.dist-info/top_level.txt
aioruz-0.8.0.dist-info/RECORD
