Metadata-Version: 2.1
Name: aioruz
Version: 0.8.0
Summary: Async HSE RUZ API client for Python3
Home-page: https://github.com/mitinarseny/aioruz
Author: Arseny Mitin
Author-email: mitinarseny@gmail.com
License: UNKNOWN
Platform: UNKNOWN
Classifier: Programming Language :: Python :: 3
Classifier: License :: OSI Approved :: MIT License
Classifier: Operating System :: OS Independent
Requires-Dist: aiohttp (==3.4.2)
Requires-Dist: asyncio (==3.4.3)
